saate_matne/__init__.py
saate_matne/saate_matne.py
saate_matne-1.0.0.dist-info/METADATA
saate_matne-1.0.0.dist-info/WHEEL
saate_matne-1.0.0.dist-info/top_level.txt
saate_matne-1.0.0.dist-info/RECORD
