Metadata-Version: 2.1
Name: saate-matne
Version: 1.0.0
Summary: A library for formatted time display in English and Persian with Night and Day themes
Home-page: UNKNOWN
Author: Fared Baktash
Author-email: faredba@outlook.com
License: MIT
Platform: UNKNOWN
Classifier: Programming Language :: Python :: 3
Classifier: License :: OSI Approved :: MIT License
Classifier: Operating System :: OS Independent
Requires-Dist: colorama
Requires-Dist: datetime
